taskcask/__init__.py
taskcask/cli/__init__.py
taskcask/cli/main.py
taskcask/cli/commands/__init__.py
taskcask/cli/commands/run.py
taskcask/executors/__init__.py
taskcask/executors/class_loader.py
taskcask/executors/executor.py
taskcask/executors/factory.py
taskcask/operations/__init__.py
taskcask/operations/run.py
taskcask/stdlib/__init__.py
taskcask/stdlib/executors/__init__.py
taskcask/stdlib/executors/class_loader.py
taskcask/stdlib/executors/system_command.py
taskcask/stdlib/task_templates/__init__.py
taskcask/stdlib/task_templates/class_loader.py
taskcask/stdlib/task_templates/system_command.py
taskcask/task_templates/__init__.py
taskcask/task_templates/class_loader.py
taskcask/task_templates/factory.py
taskcask/task_templates/system_command.py
taskcask/task_templates/task_template.py
taskcask-0.0.1.dist-info/METADATA
taskcask-0.0.1.dist-info/WHEEL
taskcask-0.0.1.dist-info/entry_points.txt
taskcask-0.0.1.dist-info/licenses/LICENSE
taskcask-0.0.1.dist-info/RECORD
